surface_sim/__init__.py
surface_sim/circuit_blocks/__init__.py
surface_sim/circuit_blocks/decorators.py
surface_sim/circuit_blocks/rot_surface_code_css.py
surface_sim/circuit_blocks/rot_surface_code_xzzx.py
surface_sim/circuit_blocks/small_stellated_dodecahedron_code.py
surface_sim/circuit_blocks/unrot_surface_code_css.py
surface_sim/circuit_blocks/util.py
surface_sim/detectors/__init__.py
surface_sim/detectors/detectors.py
surface_sim/experiments/__init__.py
surface_sim/experiments/arbitrary_experiment.py
surface_sim/experiments/rot_surface_code_css.py
surface_sim/experiments/rot_surface_code_xzzx.py
surface_sim/experiments/rot_surface_code_xzzx_google.py
surface_sim/experiments/small_stellated_dodecahedron_code.py
surface_sim/experiments/templates.py
surface_sim/experiments/unrot_surface_code_css.py
surface_sim/layouts/__init__.py
surface_sim/layouts/layout.py
surface_sim/layouts/operations.py
surface_sim/layouts/plotter.py
surface_sim/layouts/util.py
surface_sim/layouts/library/__init__.py
surface_sim/layouts/library/rot_surface_codes.py
surface_sim/layouts/library/small_stellated_dodecahedron_code.py
surface_sim/layouts/library/unrot_surface_codes.py
surface_sim/layouts/library/util.py
surface_sim/log_gates/__init__.py
surface_sim/log_gates/rot_surface_code_css.py
surface_sim/log_gates/small_stellated_dodecahedron_code.py
surface_sim/log_gates/unrot_surface_code_css.py
surface_sim/log_gates/util.py
surface_sim/models/__init__.py
surface_sim/models/library.py
surface_sim/models/model.py
surface_sim/models/util.py
surface_sim/setup/__init__.py
surface_sim/setup/library.py
surface_sim/setup/setup.py
surface_sim/util/__init__.py
surface_sim/util/circuit_operations.py
surface_sim/util/data_gen.py
surface_sim/util/observables.py
surface_sim-0.9.1.dist-info/licenses/LICENSE
surface_sim-0.9.1.dist-info/METADATA
surface_sim-0.9.1.dist-info/WHEEL
surface_sim-0.9.1.dist-info/top_level.txt
surface_sim-0.9.1.dist-info/RECORD
