Metadata-Version: 2.4
Name: surface-sim
Version: 0.9.1
Summary: Suface code simulations package
Author-email: Marc Serra Peralta <marcserraperalta@gmail.com>, Boris Varbanov <b.m.varbanov@gmail.com>
Maintainer-email: Marc Serra Peralta <marcserraperalta@gmail.com>
License: MIT License
Keywords: quantum,error correction,surface code,stabilizer simulation
Requires-Python: >=3.10
License-File: LICENSE
Requires-Dist: numpy
Requires-Dist: xarray
Requires-Dist: networkx
Requires-Dist: scipy
Requires-Dist: matplotlib
Requires-Dist: PyYAML
Requires-Dist: netCDF4
Requires-Dist: stim>=1.14.0
Requires-Dist: galois
Provides-Extra: dev
Requires-Dist: pip-tools; extra == "dev"
Requires-Dist: pytest; extra == "dev"
Requires-Dist: black; extra == "dev"
Requires-Dist: pytest-black; extra == "dev"
Requires-Dist: flake8; extra == "dev"
Requires-Dist: flake8-print; extra == "dev"
Requires-Dist: pytest-flake8; extra == "dev"
Requires-Dist: gprof2dot; extra == "dev"
Dynamic: license-file
